sparc/curation/__init__.py
sparc/curation/tools/__init__.py
sparc/curation/tools/context_annotations.py
sparc/curation/tools/definitions.py
sparc/curation/tools/errors.py
sparc/curation/tools/plot_annotations.py
sparc/curation/tools/plot_utilities.py
sparc/curation/tools/scaffold_annotations.py
sparc/curation/tools/utilities.py
sparc/curation/tools/helpers/__init__.py
sparc/curation/tools/helpers/base.py
sparc/curation/tools/helpers/error_helper.py
sparc/curation/tools/helpers/file_helper.py
sparc/curation/tools/helpers/manifest_helper.py
sparc/curation/tools/models/__init__.py
sparc/curation/tools/models/contextinfo.py
sparc/curation/tools/models/plot.py
sparc_curation_tools-0.7.9.dist-info/licenses/LICENSE
sparc_curation_tools-0.7.9.dist-info/METADATA
sparc_curation_tools-0.7.9.dist-info/WHEEL
sparc_curation_tools-0.7.9.dist-info/entry_points.txt
sparc_curation_tools-0.7.9.dist-info/top_level.txt
sparc_curation_tools-0.7.9.dist-info/RECORD
