Metadata-Version: 2.4
Name: sparc-curation-tools
Version: 0.7.9
Summary: A collection of tools to help with curating SPARC datasets.
Home-page: https://github.com/ABI-Software/sparc-curation-tools.git
Author: Hugh Sorby
Author-email: h.sorby@auckland.ac.nz
License: Apache Software License
License-File: LICENSE
Requires-Dist: pandas
Requires-Dist: openpyxl
Requires-Dist: tabulate
Requires-Dist: plotly
Requires-Dist: kaleido!=0.2.1
Provides-Extra: test
Requires-Dist: dulwich; extra == "test"
Dynamic: author
Dynamic: author-email
Dynamic: description
Dynamic: description-content-type
Dynamic: home-page
Dynamic: license
Dynamic: license-file
Dynamic: provides-extra
Dynamic: requires-dist
Dynamic: summary
